<xml xmlns="http://www.w3.org/1999/xhtml">
  <block type="movement_forward" id="1" x="117" y="23">
    <next>
      <block type="robot_delay" id="2" inline="true">
        <value name="DELAY">
          <block type="math_number" id="3">
            <field name="NUM">2000</field>
          </block>
        </value>
        <next>
          <block type="movement_right" id="4">
            <next>
              <block type="robot_delay" id="5" inline="true">
                <value name="DELAY">
                  <block type="math_number" id="6">
                    <field name="NUM">2000</field>
                  </block>
                </value>
                <next>
                  <block type="movement_left" id="29">
                    <next>
                      <block type="robot_delay" id="8" inline="true">
                        <value name="DELAY">
                          <block type="math_number" id="9">
                            <field name="NUM">2000</field>
                          </block>
                        </value>
                        <next>
                          <block type="movement_forward" id="39">
                            <next>
                              <block type="robot_delay" id="41" inline="true">
                                <value name="DELAY">
                                  <block type="math_number" id="48">
                                    <field name="NUM">2000</field>
                                  </block>
                                </value>
                                <next>
                                  <block type="oled_cleardisplay" id="10">
                                    <next>
                                      <block type="oled_drawnumber" id="17" inline="true">
                                        <value name="NUMBER">
                                          <block type="sensor_spectrometer" id="18">
                                            <field name="LIGHT">RED</field>
                                          </block>
                                        </value>
                                        <next>
                                          <block type="movement_stop" id="19"></block>
                                        </next>
                                      </block>
                                    </next>
                                  </block>
                                </next>
                              </block>
                            </next>
                          </block>
                        </next>
                      </block>
                    </next>
                  </block>
                </next>
              </block>
            </next>
          </block>
        </next>
      </block>
    </next>
  </block>
</xml>